eulerangles/__init__.py
eulerangles/base.py
eulerangles/constants.py
eulerangles/interface.py
eulerangles/utils.py
eulerangles/version.py
eulerangles/math/__init__.py
eulerangles/math/constants.py
eulerangles/math/eulers_to_eulers.py
eulerangles/math/eulers_to_rotation_matrix.py
eulerangles/math/rotation_matrix_to_eulers.py
eulerangles/math/rotation_matrices/__init__.py
eulerangles/math/rotation_matrices/angle_to_matrix.py
eulerangles/math/rotation_matrices/rotation_matrix_composition.py
eulerangles/math/rotation_matrices/utils.py
eulerangles-1.0.2.dist-info/LICENSE.txt
eulerangles-1.0.2.dist-info/METADATA
eulerangles-1.0.2.dist-info/WHEEL
eulerangles-1.0.2.dist-info/top_level.txt
eulerangles-1.0.2.dist-info/RECORD
