Metadata-Version: 2.1
Name: eulerangles
Version: 1.0.2
Summary: Simplify the handling of large sets of Euler angles in Python    
Home-page: https://github.com/alisterburt/eulerangles
Author: Alister Burt
Author-email: alisterburt@gmail.com
License: BSD 3-Clause License
Keywords: transformation,euler angles,eulerian angles,cryo-EM,cryo-ET
Platform: UNKNOWN
Classifier: Intended Audience :: Developers
Classifier: License :: OSI Approved :: BSD License
Classifier: Programming Language :: Python :: 3
Classifier: Programming Language :: Python :: 3.6
Classifier: Programming Language :: Python :: 3.7
Classifier: Programming Language :: Python :: 3.8
